{
	"$schema": "http://schema.management.azure.com/schemas/2015-01-01/deploymentTemplate.json#",
	"contentVersion": "1.0.0.0",
	"parameters": {
		"factoryName": {
			"type": "string",
			"metadata": "Data Factory name",
			"defaultValue": "rebecca-emory-msba"
		},
		"blb_msba_source_connectionString": {
			"type": "secureString",
			"metadata": "Secure string for 'connectionString' of 'blb_msba_source'"
		},
		"rebecca_msba_db_connectionString": {
			"type": "secureString",
			"metadata": "Secure string for 'connectionString' of 'rebecca_msba_db'"
		},
		"blb_msba_storage2_connectionString": {
			"type": "secureString",
			"metadata": "Secure string for 'connectionString' of 'blb_msba_storage2'"
		}
	},
	"variables": {
		"factoryId": "[concat('Microsoft.DataFactory/factories/', parameters('factoryName'))]"
	},
	"resources": [
		{
			"name": "[concat(parameters('factoryName'), '/blb_msba_source')]",
			"type": "Microsoft.DataFactory/factories/linkedServices",
			"apiVersion": "2018-06-01",
			"properties": {
				"annotations": [],
				"type": "AzureBlobStorage",
				"typeProperties": {
					"connectionString": "[parameters('blb_msba_source_connectionString')]"
				}
			},
			"dependsOn": []
		},
		{
			"name": "[concat(parameters('factoryName'), '/rebecca_msba_db')]",
			"type": "Microsoft.DataFactory/factories/linkedServices",
			"apiVersion": "2018-06-01",
			"properties": {
				"annotations": [],
				"type": "AzureSqlDatabase",
				"typeProperties": {
					"connectionString": "[parameters('rebecca_msba_db_connectionString')]"
				}
			},
			"dependsOn": []
		},
		{
			"name": "[concat(parameters('factoryName'), '/blb_msba_storage2')]",
			"type": "Microsoft.DataFactory/factories/linkedServices",
			"apiVersion": "2018-06-01",
			"properties": {
				"annotations": [],
				"type": "AzureBlobStorage",
				"typeProperties": {
					"connectionString": "[parameters('blb_msba_storage2_connectionString')]"
				}
			},
			"dependsOn": []
		},
		{
			"name": "[concat(parameters('factoryName'), '/AzureSqlTable1')]",
			"type": "Microsoft.DataFactory/factories/datasets",
			"apiVersion": "2018-06-01",
			"properties": {
				"linkedServiceName": {
					"referenceName": "rebecca_msba_db",
					"type": "LinkedServiceReference"
				},
				"annotations": [],
				"type": "AzureSqlTable",
				"schema": [],
				"typeProperties": {
					"schema": "dbo",
					"table": "shipments"
				}
			},
			"dependsOn": [
				"[concat(variables('factoryId'), '/linkedServices/rebecca_msba_db')]"
			]
		},
		{
			"name": "[concat(parameters('factoryName'), '/ds_shipment')]",
			"type": "Microsoft.DataFactory/factories/datasets",
			"apiVersion": "2018-06-01",
			"properties": {
				"linkedServiceName": {
					"referenceName": "blb_msba_source",
					"type": "LinkedServiceReference"
				},
				"annotations": [],
				"type": "DelimitedText",
				"typeProperties": {
					"location": {
						"type": "AzureBlobStorageLocation",
						"fileName": "Shipments.csv",
						"container": "msbasource"
					},
					"columnDelimiter": ",",
					"escapeChar": "\\",
					"firstRowAsHeader": true,
					"quoteChar": "\""
				},
				"schema": []
			},
			"dependsOn": [
				"[concat(variables('factoryId'), '/linkedServices/blb_msba_source')]"
			]
		},
		{
			"name": "[concat(parameters('factoryName'), '/get_metadata')]",
			"type": "Microsoft.DataFactory/factories/datasets",
			"apiVersion": "2018-06-01",
			"properties": {
				"linkedServiceName": {
					"referenceName": "blb_msba_storage2",
					"type": "LinkedServiceReference"
				},
				"annotations": [],
				"type": "DelimitedText",
				"typeProperties": {
					"location": {
						"type": "AzureBlobStorageLocation",
						"container": "msbasource"
					},
					"columnDelimiter": ",",
					"escapeChar": "\\",
					"quoteChar": "\""
				},
				"schema": []
			},
			"dependsOn": [
				"[concat(variables('factoryId'), '/linkedServices/blb_msba_storage2')]"
			]
		},
		{
			"name": "[concat(parameters('factoryName'), '/input_file')]",
			"type": "Microsoft.DataFactory/factories/datasets",
			"apiVersion": "2018-06-01",
			"properties": {
				"linkedServiceName": {
					"referenceName": "blb_msba_storage2",
					"type": "LinkedServiceReference"
				},
				"parameters": {
					"FileName": {
						"type": "string"
					}
				},
				"annotations": [],
				"type": "DelimitedText",
				"typeProperties": {
					"location": {
						"type": "AzureBlobStorageLocation",
						"fileName": {
							"value": "@dataset().FileName",
							"type": "Expression"
						},
						"container": "msbasource"
					},
					"columnDelimiter": ",",
					"escapeChar": "\\",
					"firstRowAsHeader": true,
					"quoteChar": "\""
				},
				"schema": [
					{
						"name": "Worker_Ref_ID",
						"type": "String"
					},
					{
						"name": "Bonus_Date",
						"type": "String"
					},
					{
						"name": "Bonus_Amount",
						"type": "String"
					}
				]
			},
			"dependsOn": [
				"[concat(variables('factoryId'), '/linkedServices/blb_msba_storage2')]"
			]
		},
		{
			"name": "[concat(parameters('factoryName'), '/AzureSqlTable2')]",
			"type": "Microsoft.DataFactory/factories/datasets",
			"apiVersion": "2018-06-01",
			"properties": {
				"linkedServiceName": {
					"referenceName": "rebecca_msba_db",
					"type": "LinkedServiceReference"
				},
				"parameters": {
					"TableName": {
						"type": "string"
					}
				},
				"annotations": [],
				"type": "AzureSqlTable",
				"schema": [],
				"typeProperties": {
					"schema": "dbo",
					"table": {
						"value": "@dataset().TableName",
						"type": "Expression"
					}
				}
			},
			"dependsOn": [
				"[concat(variables('factoryId'), '/linkedServices/rebecca_msba_db')]"
			]
		},
		{
			"name": "[concat(parameters('factoryName'), '/pl_load_shipment_to_azure')]",
			"type": "Microsoft.DataFactory/factories/pipelines",
			"apiVersion": "2018-06-01",
			"properties": {
				"activities": [
					{
						"name": "copydata_shipmenttotable",
						"type": "Copy",
						"dependsOn": [],
						"policy": {
							"timeout": "7.00:00:00",
							"retry": 0,
							"retryIntervalInSeconds": 30,
							"secureOutput": false,
							"secureInput": false
						},
						"userProperties": [],
						"typeProperties": {
							"source": {
								"type": "DelimitedTextSource",
								"storeSettings": {
									"type": "AzureBlobStorageReadSettings",
									"recursive": true,
									"enablePartitionDiscovery": false
								},
								"formatSettings": {
									"type": "DelimitedTextReadSettings"
								}
							},
							"sink": {
								"type": "AzureSqlSink",
								"writeBehavior": "insert",
								"sqlWriterUseTableLock": true,
								"tableOption": "autoCreate",
								"disableMetricsCollection": false
							},
							"enableStaging": false,
							"translator": {
								"type": "TabularTranslator",
								"mappings": [
									{
										"source": {
											"name": "ID Number",
											"type": "String",
											"physicalType": "String"
										},
										"sink": {
											"name": "id_number",
											"type": "Int32",
											"physicalType": "int"
										}
									},
									{
										"source": {
											"name": "Type",
											"type": "String",
											"physicalType": "String"
										},
										"sink": {
											"name": "type",
											"type": "String",
											"physicalType": "varchar"
										}
									},
									{
										"source": {
											"name": "Commodity",
											"type": "String",
											"physicalType": "String"
										},
										"sink": {
											"name": "commodity",
											"type": "String",
											"physicalType": "varchar"
										}
									},
									{
										"source": {
											"name": "BOL",
											"type": "String",
											"physicalType": "String"
										},
										"sink": {
											"name": "BOL",
											"type": "String",
											"physicalType": "varchar"
										}
									},
									{
										"source": {
											"name": "Origin City",
											"type": "String",
											"physicalType": "String"
										},
										"sink": {
											"name": "origin_city",
											"type": "String",
											"physicalType": "varchar"
										}
									},
									{
										"source": {
											"name": "Origin State",
											"type": "String",
											"physicalType": "String"
										},
										"sink": {
											"name": "origin_state",
											"type": "String",
											"physicalType": "varchar"
										}
									},
									{
										"source": {
											"name": "Origin Zip",
											"type": "String",
											"physicalType": "String"
										},
										"sink": {
											"name": "origin_zip",
											"type": "Int32",
											"physicalType": "int"
										}
									},
									{
										"source": {
											"name": "Destination Zip",
											"type": "String",
											"physicalType": "String"
										},
										"sink": {
											"name": "destination_zip",
											"type": "Int32",
											"physicalType": "int"
										}
									},
									{
										"source": {
											"name": "Mode",
											"type": "String",
											"physicalType": "String"
										},
										"sink": {
											"name": "mode",
											"type": "String",
											"physicalType": "varchar"
										}
									},
									{
										"source": {
											"name": " Weight ",
											"type": "String",
											"physicalType": "String"
										},
										"sink": {
											"name": "weight",
											"type": "Int32",
											"physicalType": "int"
										}
									},
									{
										"source": {
											"name": "Freight Class",
											"type": "String",
											"physicalType": "String"
										},
										"sink": {
											"name": "freight_class",
											"type": "Double",
											"physicalType": "float"
										}
									},
									{
										"source": {
											"name": "Pallets",
											"type": "String",
											"physicalType": "String"
										},
										"sink": {
											"name": "pallets",
											"type": "Int32",
											"physicalType": "int"
										}
									},
									{
										"source": {
											"name": "Ship Date",
											"type": "String",
											"physicalType": "String"
										},
										"sink": {
											"name": "ship_date",
											"type": "DateTime",
											"physicalType": "datetime"
										}
									},
									{
										"source": {
											"name": "Invoice Date",
											"type": "String",
											"physicalType": "String"
										},
										"sink": {
											"name": "invoice_date",
											"type": "DateTime",
											"physicalType": "datetime"
										}
									}
								],
								"typeConversion": true,
								"typeConversionSettings": {
									"allowDataTruncation": true,
									"treatBooleanAsNumber": false
								}
							}
						},
						"inputs": [
							{
								"referenceName": "ds_shipment",
								"type": "DatasetReference",
								"parameters": {}
							}
						],
						"outputs": [
							{
								"referenceName": "AzureSqlTable1",
								"type": "DatasetReference",
								"parameters": {}
							}
						]
					}
				],
				"policy": {
					"elapsedTimeMetric": {},
					"cancelAfter": {}
				},
				"annotations": []
			},
			"dependsOn": [
				"[concat(variables('factoryId'), '/datasets/ds_shipment')]",
				"[concat(variables('factoryId'), '/datasets/AzureSqlTable1')]"
			]
		},
		{
			"name": "[concat(parameters('factoryName'), '/pipeline_load_multiple_tables')]",
			"type": "Microsoft.DataFactory/factories/pipelines",
			"apiVersion": "2018-06-01",
			"properties": {
				"activities": [
					{
						"name": "Get Metadata1",
						"type": "GetMetadata",
						"dependsOn": [],
						"policy": {
							"timeout": "7.00:00:00",
							"retry": 0,
							"retryIntervalInSeconds": 30,
							"secureOutput": false,
							"secureInput": false
						},
						"userProperties": [],
						"typeProperties": {
							"dataset": {
								"referenceName": "get_metadata",
								"type": "DatasetReference",
								"parameters": {}
							},
							"fieldList": [
								"childItems"
							],
							"storeSettings": {
								"type": "AzureBlobStorageReadSettings",
								"enablePartitionDiscovery": false
							},
							"formatSettings": {
								"type": "DelimitedTextReadSettings"
							}
						}
					},
					{
						"name": "ForEach1",
						"type": "ForEach",
						"dependsOn": [
							{
								"activity": "Get Metadata1",
								"dependencyConditions": [
									"Succeeded"
								]
							}
						],
						"userProperties": [],
						"typeProperties": {
							"items": {
								"value": "@activity('Get Metadata1').output.childItems",
								"type": "Expression"
							},
							"activities": [
								{
									"name": "Copy data1",
									"type": "Copy",
									"dependsOn": [],
									"policy": {
										"timeout": "7.00:00:00",
										"retry": 0,
										"retryIntervalInSeconds": 30,
										"secureOutput": false,
										"secureInput": false
									},
									"userProperties": [],
									"typeProperties": {
										"source": {
											"type": "DelimitedTextSource",
											"storeSettings": {
												"type": "AzureBlobStorageReadSettings",
												"recursive": true,
												"enablePartitionDiscovery": false
											},
											"formatSettings": {
												"type": "DelimitedTextReadSettings"
											}
										},
										"sink": {
											"type": "AzureSqlSink",
											"writeBehavior": "insert",
											"sqlWriterUseTableLock": false,
											"tableOption": "autoCreate",
											"disableMetricsCollection": false
										},
										"enableStaging": false,
										"translator": {
											"type": "TabularTranslator",
											"typeConversion": true,
											"typeConversionSettings": {
												"allowDataTruncation": true,
												"treatBooleanAsNumber": false
											}
										}
									},
									"inputs": [
										{
											"referenceName": "input_file",
											"type": "DatasetReference",
											"parameters": {
												"FileName": {
													"value": "@item().name",
													"type": "Expression"
												}
											}
										}
									],
									"outputs": [
										{
											"referenceName": "AzureSqlTable2",
											"type": "DatasetReference",
											"parameters": {
												"TableName": {
													"value": "@concat(replace(item().name,'.csv',''))",
													"type": "Expression"
												}
											}
										}
									]
								}
							]
						}
					}
				],
				"policy": {
					"elapsedTimeMetric": {},
					"cancelAfter": {}
				},
				"annotations": []
			},
			"dependsOn": [
				"[concat(variables('factoryId'), '/datasets/get_metadata')]",
				"[concat(variables('factoryId'), '/datasets/input_file')]",
				"[concat(variables('factoryId'), '/datasets/AzureSqlTable2')]"
			]
		}
	]
}